{
"biota": "Biologie",
"boundaries": "Grenzen",
"climatologymeteorologyatmosphere": "Athmosphäre",
"economy": "Wirtschaft",
"elevation": "Höhenangaben",
"environment": "Umwelt",
"farming": "Landwirtschaft",
"geoscientificinformation": "Geowissenschaften",
"health": "Gesundheitswesen",
"imagerybasemapsearthcover": "Oberflächenbeschreibung",
"inlandwaters": "Binnengewässer",
"location": "Ortsangaben",
"oceans": "Meere",
"planningcadastre": "Planungsunterlagen,Kataster",
"society": "Gesellschaft",
"structure": "Bauwerke",
"transportation": "Verkehrswesen",
"utilitiescommunication": "Ver- und Entsorgung,Kommunikation"
}